lexorank/__init__.py
lexorank/base.py
lexorank/decimal.py
lexorank/decimal_test.py
lexorank/integer.py
lexorank/integer_test.py
lexorank/lexorank.py
lexorank/lexorank_test.py
lexorank/py.typed
lexorank_py-0.1.1.dist-info/LICENSE
lexorank_py-0.1.1.dist-info/METADATA
lexorank_py-0.1.1.dist-info/WHEEL
lexorank_py-0.1.1.dist-info/top_level.txt
lexorank_py-0.1.1.dist-info/RECORD
