Metadata-Version: 2.1
Name: lexorank-py
Version: 0.1.1
Summary: lexorank
Author-email: Hyeonki Hong <hhk7734@gmail.com>
License: MIT License
Project-URL: repository, https://github.com/hhk7734/lexorank.py
Keywords: lexorank
Classifier: Programming Language :: Python :: 3
Classifier: Intended Audience :: Developers
Requires-Python: <4.0,>=3.10
License-File: LICENSE
